admin_page_lock/__init__.py
admin_page_lock/admin.py
admin_page_lock/apps.py
admin_page_lock/handlers.py
admin_page_lock/settings.py
admin_page_lock/urls.py
admin_page_lock/utils.py
admin_page_lock/views.py
admin_page_lock/__pycache__/__init__.cpython-39.pyc
admin_page_lock/migrations/0001_initial.py
admin_page_lock/migrations/0002_auto_20170605_1350.py
admin_page_lock/migrations/0003_databasepagelockmodel_tab_counter.py
admin_page_lock/migrations/0004_databasepagelockmodel_last_checked.py
admin_page_lock/migrations/__init__.py
admin_page_lock/mixins/__init__.py
admin_page_lock/mixins/admin_mixin.py
admin_page_lock/mixins/base_mixin.py
admin_page_lock/mixins/view_mixin.py
admin_page_lock/models/__init__.py
admin_page_lock/models/base_model.py
admin_page_lock/models/database_model.py
admin_page_lock/models/redis_model.py
admin_page_lock/static/js/page_lock.js
admin_page_lock/templates/admin_page_lock/page_lock_bar_bootstrap.html
admin_page_lock/templates/admin_page_lock/page_lock_bar_plain.html
admin_page_lock/templatetags/__init__.py
admin_page_lock/templatetags/page_lock_bar.py
django_admin_page_lock-2.1.7.dist-info/AUTHORS
django_admin_page_lock-2.1.7.dist-info/LICENSE
django_admin_page_lock-2.1.7.dist-info/METADATA
django_admin_page_lock-2.1.7.dist-info/WHEEL
django_admin_page_lock-2.1.7.dist-info/top_level.txt
django_admin_page_lock-2.1.7.dist-info/RECORD
