Metadata-Version: 2.1
Name: django-admin-page-lock
Version: 2.1.7
Summary: Page Lock application prevents users from editing a page while it is being edited by someone else. The application is tailored to django admin implementation.
Home-page: https://github.com/ShowMax/django-admin-page-lock
Author: Vojtech Stefka
Author-email: oss+djangopage@showmax.com
License: Apache License, Version 2.0
Keywords: django,admin,locking,concurrency
Platform: any
Classifier: Environment :: Web Environment
Classifier: Intended Audience :: Developers
Classifier: License :: OSI Approved :: Apache Software License
Classifier: Framework :: Django :: 1.8
Classifier: Framework :: Django :: 1.9
Classifier: Framework :: Django :: 1.11
Classifier: Framework :: Django :: 2.0
Classifier: Programming Language :: Python :: 2.7
Classifier: Programming Language :: Python :: 3.6
Classifier: Programming Language :: Python :: 3.7
Classifier: Topic :: Software Development :: Libraries :: Python Modules
License-File: LICENSE
License-File: AUTHORS
